dmt_htwk/__init__.py
dmt_htwk-1.0.0.dist-info/METADATA
dmt_htwk-1.0.0.dist-info/WHEEL
dmt_htwk-1.0.0.dist-info/licenses/LICENSE
dmt_htwk-1.0.0.dist-info/RECORD
