Metadata-Version: 2.1
Name: dmt_htwk
Version: 1.0.0
Summary: Eine IPython-Erweiterung, welche die Verbidung zum Assessment-System DMT ermöglicht und Aufgaben dynamisch im Notebook erstellt.
Author-email: Martin Petersohn <martin.petersohn@stud.htwk-leipzig.de>
License-File: LICENSE
Classifier: License :: OSI Approved :: MIT License
Classifier: Operating System :: OS Independent
Classifier: Programming Language :: Python :: 3
Requires-Python: >=3.9
